django_hardcopy-0.1.4.dist-info/DESCRIPTION.rst
django_hardcopy-0.1.4.dist-info/METADATA
django_hardcopy-0.1.4.dist-info/RECORD
django_hardcopy-0.1.4.dist-info/WHEEL
django_hardcopy-0.1.4.dist-info/metadata.json
django_hardcopy-0.1.4.dist-info/top_level.txt
hardcopy/__init__.py
hardcopy/conf.py
hardcopy/views.py
