Metadata-Version: 2.0
Name: django-hardcopy
Version: 0.1.4
Summary: Django wrapper and utilities for generating PDF and PNG files with context using the headless chrome or chromium browser.
Home-page: https://github.com/loftylabs/django-hardcopy
Author: Casey Kinsey / Lofty Labs
Author-email: casey@hirelofty.com
License: UNKNOWN
Platform: UNKNOWN
